ragno/Ragno.py
ragno/__init__.py
Ragno-1.6.dist-info/LICENSE
Ragno-1.6.dist-info/METADATA
Ragno-1.6.dist-info/WHEEL
Ragno-1.6.dist-info/entry_points.txt
Ragno-1.6.dist-info/top_level.txt
Ragno-1.6.dist-info/RECORD
