Metadata-Version: 2.1
Name: Ragno
Version: 1.6
Summary: Ragno Passive URL Crawler - Python Module
Home-page: https://github.com/PushpenderIndia/ragno
Author: Pushpender Singh
Author-email: pushpendersingh@protonmail.com
License: GNU General Public License v3 (GPLv3)
Keywords: ragno,bug bounty,http,pentesting,security,recon,passive information gathering,passive recon
Classifier: Development Status :: 5 - Production/Stable
Classifier: Intended Audience :: Developers
Classifier: Intended Audience :: Information Technology
Classifier: Operating System :: OS Independent
Classifier: Topic :: Security
Classifier: License :: OSI Approved :: GNU General Public License v3 (GPLv3)
Classifier: Programming Language :: Python :: 3
Classifier: Programming Language :: Python :: 3.4
Classifier: Programming Language :: Python :: 3.5
Classifier: Programming Language :: Python :: 3.6
Classifier: Programming Language :: Python :: 3.7
Classifier: Programming Language :: Python :: 3.8
Classifier: Programming Language :: Python :: 3.9
License-File: LICENSE
Requires-Dist: argparse
Requires-Dist: colorama
Requires-Dist: numpy
Requires-Dist: pyfiglet
Requires-Dist: requests
